archive/__init__.py
whip/__init__.py
whip/__main__.py
whip/static/1.mp3
whip/static/2.mp3
whip/static/3.mp3
whip/static/4.mp3
whip/static/5.mp3
whip_sound-1.0.5.dist-info/METADATA
whip_sound-1.0.5.dist-info/WHEEL
whip_sound-1.0.5.dist-info/dependency_links.txt
whip_sound-1.0.5.dist-info/entry_points.txt
whip_sound-1.0.5.dist-info/top_level.txt
whip_sound-1.0.5.dist-info/RECORD
