Metadata-Version: 2.1
Name: whip-sound
Version: 1.0.5
Summary: Whip Sound Command line application that makes whip sound on providing different numeric options
Home-page: https://github.com/anandtripathi5/whip-sound
Author: Anand Tripathi
Author-email: anand.tripathi507@gmail.com
License: MIT
Download-URL: https://github.com/anandtripathi5/whip-sound/archive/1.0.5.tar.gz
Platform: UNKNOWN
Classifier: License :: OSI Approved :: MIT License
Classifier: Programming Language :: Python :: 2.7
Classifier: Programming Language :: Python :: 3
Classifier: Programming Language :: Python :: 3.7
Requires-Python: >=2.7
Requires-Dist: click (==8.0.3)
Requires-Dist: pyobjc (==8.0)
Requires-Dist: playsound (==1.3.0)
